ezvalue/__init__.py
ezvalue-0.1.3.dist-info/DESCRIPTION.rst
ezvalue-0.1.3.dist-info/METADATA
ezvalue-0.1.3.dist-info/RECORD
ezvalue-0.1.3.dist-info/WHEEL
ezvalue-0.1.3.dist-info/metadata.json
ezvalue-0.1.3.dist-info/top_level.txt
