Metadata-Version: 2.0
Name: ezvalue
Version: 0.1.3
Summary: An elegant and powerfull implementation of a value object.
Home-page: https://github.com/snah/ezvalue
Author: Hans Maree
Author-email: hans.maree@gmail.com
License: MIT
Keywords: value valueobject immutable
Platform: UNKNOWN
Classifier: Development Status :: 4 - Beta
Classifier: Intended Audience :: Developers
Classifier: Topic :: Software Development
Classifier: Programming Language :: Python :: 3
Classifier: Programming Language :: Python :: 3.2
Classifier: Programming Language :: Python :: 3.3
Classifier: Programming Language :: Python :: 3.4
Classifier: Programming Language :: Python :: 3.5
Classifier: Programming Language :: Python :: 3.6
